SwampClient/__init__.py
SwampClient/client.py
SwampClient/config.py
SwampClient/logger.py
swampclient-0.1.3.dist-info/METADATA
swampclient-0.1.3.dist-info/WHEEL
swampclient-0.1.3.dist-info/licenses/LICENSE
swampclient-0.1.3.dist-info/RECORD
