Metadata-Version: 2.4
Name: SwampClient
Version: 0.1.3
Summary: An MQTT client library built as a wrapper around Paho MQTT, configurable via environment variables, supporting JSONata transformations and timestamp handling through Zeitgleich.
Project-URL: source, https://git.ift.tuwien.ac.at/lab/pub/pypi/swampclient
Author-email: Jakob Friedl <jakob.friedl@tuwien.ac.at>
License-Expression: MIT
License-File: LICENSE
Keywords: asyncio,client,jsonata,mqtt,time series,timestamp
Classifier: Development Status :: 2 - Pre-Alpha
Classifier: Intended Audience :: Developers
Classifier: License :: OSI Approved :: MIT License
Classifier: Operating System :: OS Independent
Classifier: Programming Language :: Python :: 3
Classifier: Programming Language :: Python :: 3.6
Classifier: Programming Language :: Python :: 3.7
Classifier: Programming Language :: Python :: 3.8
Classifier: Programming Language :: Python :: 3.9
Classifier: Topic :: Communications :: Telephony
Classifier: Topic :: Software Development :: Libraries :: Python Modules
Requires-Python: >=3.6
Requires-Dist: jsonata-python>=0.5.2
Requires-Dist: paho-mqtt>=1.6.1
Requires-Dist: python-dotenv>=0.19.2
Requires-Dist: zeitgleich>=0.1.0
